action_test/__init__.py
action_test/email_server.py
action_test/helo.py
actiontest_pipeline-5.0.0.dist-info/METADATA
actiontest_pipeline-5.0.0.dist-info/WHEEL
actiontest_pipeline-5.0.0.dist-info/RECORD
